{
  "snapshot": {
    "version": 1,
    "directus": "10.8.3",
    "vendor": "postgres",
    "collections": [
      {
        "collection": "todo_items",
        "meta": {
          "accountability": "all",
          "archive_app_filter": true,
          "archive_field": null,
          "archive_value": null,
          "collapse": "open",
          "collection": "todo_items",
          "color": null,
          "display_template": null,
          "group": "todo_lists",
          "hidden": false,
          "icon": null,
          "item_duplication_fields": null,
          "note": null,
          "preview_url": null,
          "singleton": false,
          "sort": 1,
          "sort_field": null,
          "translations": null,
          "unarchive_value": null,
          "versioning": false
        },
        "schema": {
          "name": "todo_items"
        }
      },
      {
        "collection": "todo_lists",
        "meta": {
          "accountability": "all",
          "archive_app_filter": true,
          "archive_field": null,
          "archive_value": null,
          "collapse": "open",
          "collection": "todo_lists",
          "color": null,
          "display_template": null,
          "group": null,
          "hidden": false,
          "icon": null,
          "item_duplication_fields": null,
          "note": null,
          "preview_url": null,
          "singleton": false,
          "sort": 1,
          "sort_field": null,
          "translations": null,
          "unarchive_value": null,
          "versioning": false
        },
        "schema": {
          "name": "todo_lists"
        }
      }
    ],
    "fields": [
      {
        "collection": "directus_settings",
        "field": "mv_hash",
        "type": "string",
        "meta": null,
        "schema": {
          "name": "mv_hash",
          "table": "directus_settings",
          "data_type": "character varying",
          "default_value": "",
          "max_length": 255,
          "numeric_precision": null,
          "numeric_scale": null,
          "is_nullable": false,
          "is_unique": false,
          "is_primary_key": false,
          "is_generated": false,
          "generation_expression": null,
          "has_auto_increment": false,
          "foreign_key_table": null,
          "foreign_key_column": null
        }
      },
      {
        "collection": "directus_settings",
        "field": "mv_locked",
        "type": "boolean",
        "meta": null,
        "schema": {
          "name": "mv_locked",
          "table": "directus_settings",
          "data_type": "boolean",
          "default_value": false,
          "max_length": null,
          "numeric_precision": null,
          "numeric_scale": null,
          "is_nullable": false,
          "is_unique": false,
          "is_primary_key": false,
          "is_generated": false,
          "generation_expression": null,
          "has_auto_increment": false,
          "foreign_key_table": null,
          "foreign_key_column": null
        }
      },
      {
        "collection": "directus_settings",
        "field": "mv_ts",
        "type": "timestamp",
        "meta": null,
        "schema": {
          "name": "mv_ts",
          "table": "directus_settings",
          "data_type": "timestamp with time zone",
          "default_value": "2020-01-01 00:00:00+00",
          "max_length": null,
          "numeric_precision": null,
          "numeric_scale": null,
          "is_nullable": false,
          "is_unique": false,
          "is_primary_key": false,
          "is_generated": false,
          "generation_expression": null,
          "has_auto_increment": false,
          "foreign_key_table": null,
          "foreign_key_column": null
        }
      },
      {
        "collection": "directus_users",
        "field": "person_id",
        "type": "string",
        "meta": null,
        "schema": {
          "name": "person_id",
          "table": "directus_users",
          "data_type": "character varying",
          "default_value": null,
          "max_length": 36,
          "numeric_precision": null,
          "numeric_scale": null,
          "is_nullable": true,
          "is_unique": false,
          "is_primary_key": false,
          "is_generated": false,
          "generation_expression": null,
          "has_auto_increment": false,
          "foreign_key_table": null,
          "foreign_key_column": null
        }
      },
      {
        "collection": "todo_items",
        "field": "date_created",
        "type": "timestamp",
        "meta": {
          "collection": "todo_items",
          "conditions": null,
          "display": "datetime",
          "display_options": {
            "relative": true
          },
          "field": "date_created",
          "group": null,
          "hidden": true,
          "interface": "datetime",
          "note": null,
          "options": null,
          "readonly": true,
          "required": false,
          "sort": 6,
          "special": [
            "date-created"
          ],
          "translations": null,
          "validation": null,
          "validation_message": null,
          "width": "half"
        },
        "schema": {
          "name": "date_created",
          "table": "todo_items",
          "data_type": "timestamp with time zone",
          "default_value": null,
          "max_length": null,
          "numeric_precision": null,
          "numeric_scale": null,
          "is_nullable": true,
          "is_unique": false,
          "is_primary_key": false,
          "is_generated": false,
          "generation_expression": null,
          "has_auto_increment": false,
          "foreign_key_table": null,
          "foreign_key_column": null
        }
      },
      {
        "collection": "todo_items",
        "field": "id",
        "type": "integer",
        "meta": {
          "collection": "todo_items",
          "conditions": null,
          "display": null,
          "display_options": null,
          "field": "id",
          "group": null,
          "hidden": true,
          "interface": "input",
          "note": null,
          "options": null,
          "readonly": true,
          "required": false,
          "sort": 1,
          "special": null,
          "translations": null,
          "validation": null,
          "validation_message": null,
          "width": "full"
        },
        "schema": {
          "name": "id",
          "table": "todo_items",
          "data_type": "integer",
          "default_value": null,
          "max_length": null,
          "numeric_precision": 32,
          "numeric_scale": 0,
          "is_nullable": false,
          "is_unique": true,
          "is_primary_key": true,
          "is_generated": false,
          "generation_expression": null,
          "has_auto_increment": true,
          "foreign_key_table": null,
          "foreign_key_column": null
        }
      },
      {
        "collection": "todo_items",
        "field": "is_done",
        "type": "boolean",
        "meta": {
          "collection": "todo_items",
          "conditions": null,
          "display": null,
          "display_options": null,
          "field": "is_done",
          "group": null,
          "hidden": false,
          "interface": "boolean",
          "note": null,
          "options": {
            "label": "is done"
          },
          "readonly": false,
          "required": true,
          "sort": 3,
          "special": [
            "cast-boolean"
          ],
          "translations": null,
          "validation": null,
          "validation_message": null,
          "width": "full"
        },
        "schema": {
          "name": "is_done",
          "table": "todo_items",
          "data_type": "boolean",
          "default_value": false,
          "max_length": null,
          "numeric_precision": null,
          "numeric_scale": null,
          "is_nullable": true,
          "is_unique": false,
          "is_primary_key": false,
          "is_generated": false,
          "generation_expression": null,
          "has_auto_increment": false,
          "foreign_key_table": null,
          "foreign_key_column": null
        }
      },
      {
        "collection": "todo_items",
        "field": "list_id",
        "type": "uuid",
        "meta": {
          "collection": "todo_items",
          "conditions": null,
          "display": null,
          "display_options": null,
          "field": "list_id",
          "group": null,
          "hidden": false,
          "interface": "select-dropdown-m2o",
          "note": null,
          "options": {
            "template": "{{name}}"
          },
          "readonly": false,
          "required": true,
          "sort": 4,
          "special": [
            "m2o"
          ],
          "translations": null,
          "validation": null,
          "validation_message": null,
          "width": "full"
        },
        "schema": {
          "name": "list_id",
          "table": "todo_items",
          "data_type": "uuid",
          "default_value": null,
          "max_length": null,
          "numeric_precision": null,
          "numeric_scale": null,
          "is_nullable": true,
          "is_unique": false,
          "is_primary_key": false,
          "is_generated": false,
          "generation_expression": null,
          "has_auto_increment": false,
          "foreign_key_table": "todo_lists",
          "foreign_key_column": "id"
        }
      },
      {
        "collection": "todo_items",
        "field": "text",
        "type": "string",
        "meta": {
          "collection": "todo_items",
          "conditions": null,
          "display": null,
          "display_options": null,
          "field": "text",
          "group": null,
          "hidden": false,
          "interface": "input",
          "note": null,
          "options": null,
          "readonly": false,
          "required": true,
          "sort": 2,
          "special": null,
          "translations": null,
          "validation": null,
          "validation_message": null,
          "width": "full"
        },
        "schema": {
          "name": "text",
          "table": "todo_items",
          "data_type": "character varying",
          "default_value": null,
          "max_length": 255,
          "numeric_precision": null,
          "numeric_scale": null,
          "is_nullable": true,
          "is_unique": false,
          "is_primary_key": false,
          "is_generated": false,
          "generation_expression": null,
          "has_auto_increment": false,
          "foreign_key_table": null,
          "foreign_key_column": null
        }
      },
      {
        "collection": "todo_items",
        "field": "user_created",
        "type": "uuid",
        "meta": {
          "collection": "todo_items",
          "conditions": null,
          "display": "user",
          "display_options": null,
          "field": "user_created",
          "group": null,
          "hidden": true,
          "interface": "select-dropdown-m2o",
          "note": null,
          "options": {
            "template": "{{avatar.$thumbnail}} {{first_name}} {{last_name}}"
          },
          "readonly": true,
          "required": false,
          "sort": 5,
          "special": [
            "user-created"
          ],
          "translations": null,
          "validation": null,
          "validation_message": null,
          "width": "half"
        },
        "schema": {
          "name": "user_created",
          "table": "todo_items",
          "data_type": "uuid",
          "default_value": null,
          "max_length": null,
          "numeric_precision": null,
          "numeric_scale": null,
          "is_nullable": true,
          "is_unique": false,
          "is_primary_key": false,
          "is_generated": false,
          "generation_expression": null,
          "has_auto_increment": false,
          "foreign_key_table": "directus_users",
          "foreign_key_column": "id"
        }
      },
      {
        "collection": "todo_lists",
        "field": "date_created",
        "type": "timestamp",
        "meta": {
          "collection": "todo_lists",
          "conditions": null,
          "display": "datetime",
          "display_options": {
            "relative": true
          },
          "field": "date_created",
          "group": null,
          "hidden": true,
          "interface": "datetime",
          "note": null,
          "options": null,
          "readonly": true,
          "required": false,
          "sort": 4,
          "special": [
            "date-created"
          ],
          "translations": null,
          "validation": null,
          "validation_message": null,
          "width": "half"
        },
        "schema": {
          "name": "date_created",
          "table": "todo_lists",
          "data_type": "timestamp with time zone",
          "default_value": null,
          "max_length": null,
          "numeric_precision": null,
          "numeric_scale": null,
          "is_nullable": true,
          "is_unique": false,
          "is_primary_key": false,
          "is_generated": false,
          "generation_expression": null,
          "has_auto_increment": false,
          "foreign_key_table": null,
          "foreign_key_column": null
        }
      },
      {
        "collection": "todo_lists",
        "field": "id",
        "type": "uuid",
        "meta": {
          "collection": "todo_lists",
          "conditions": null,
          "display": null,
          "display_options": null,
          "field": "id",
          "group": null,
          "hidden": true,
          "interface": "input",
          "note": null,
          "options": null,
          "readonly": true,
          "required": false,
          "sort": 1,
          "special": [
            "uuid"
          ],
          "translations": null,
          "validation": null,
          "validation_message": null,
          "width": "full"
        },
        "schema": {
          "name": "id",
          "table": "todo_lists",
          "data_type": "uuid",
          "default_value": null,
          "max_length": null,
          "numeric_precision": null,
          "numeric_scale": null,
          "is_nullable": false,
          "is_unique": true,
          "is_primary_key": true,
          "is_generated": false,
          "generation_expression": null,
          "has_auto_increment": false,
          "foreign_key_table": null,
          "foreign_key_column": null
        }
      },
      {
        "collection": "todo_lists",
        "field": "name",
        "type": "string",
        "meta": {
          "collection": "todo_lists",
          "conditions": null,
          "display": null,
          "display_options": null,
          "field": "name",
          "group": null,
          "hidden": false,
          "interface": "input",
          "note": null,
          "options": null,
          "readonly": false,
          "required": true,
          "sort": 2,
          "special": null,
          "translations": null,
          "validation": null,
          "validation_message": null,
          "width": "full"
        },
        "schema": {
          "name": "name",
          "table": "todo_lists",
          "data_type": "character varying",
          "default_value": null,
          "max_length": 255,
          "numeric_precision": null,
          "numeric_scale": null,
          "is_nullable": true,
          "is_unique": false,
          "is_primary_key": false,
          "is_generated": false,
          "generation_expression": null,
          "has_auto_increment": false,
          "foreign_key_table": null,
          "foreign_key_column": null
        }
      },
      {
        "collection": "todo_lists",
        "field": "user_created",
        "type": "uuid",
        "meta": {
          "collection": "todo_lists",
          "conditions": null,
          "display": "user",
          "display_options": null,
          "field": "user_created",
          "group": null,
          "hidden": true,
          "interface": "select-dropdown-m2o",
          "note": null,
          "options": {
            "template": "{{avatar.$thumbnail}} {{first_name}} {{last_name}}"
          },
          "readonly": true,
          "required": false,
          "sort": 3,
          "special": [
            "user-created"
          ],
          "translations": null,
          "validation": null,
          "validation_message": null,
          "width": "half"
        },
        "schema": {
          "name": "user_created",
          "table": "todo_lists",
          "data_type": "uuid",
          "default_value": null,
          "max_length": null,
          "numeric_precision": null,
          "numeric_scale": null,
          "is_nullable": true,
          "is_unique": false,
          "is_primary_key": false,
          "is_generated": false,
          "generation_expression": null,
          "has_auto_increment": false,
          "foreign_key_table": "directus_users",
          "foreign_key_column": "id"
        }
      }
    ],
    "relations": [
      {
        "collection": "todo_items",
        "field": "list_id",
        "related_collection": "todo_lists",
        "meta": {
          "junction_field": null,
          "many_collection": "todo_items",
          "many_field": "list_id",
          "one_allowed_collections": null,
          "one_collection": "todo_lists",
          "one_collection_field": null,
          "one_deselect_action": "nullify",
          "one_field": null,
          "sort_field": null
        },
        "schema": {
          "table": "todo_items",
          "column": "list_id",
          "foreign_key_table": "todo_lists",
          "foreign_key_column": "id",
          "constraint_name": "todo_items_list_id_foreign",
          "on_update": "NO ACTION",
          "on_delete": "SET NULL"
        }
      },
      {
        "collection": "todo_items",
        "field": "user_created",
        "related_collection": "directus_users",
        "meta": {
          "junction_field": null,
          "many_collection": "todo_items",
          "many_field": "user_created",
          "one_allowed_collections": null,
          "one_collection": "directus_users",
          "one_collection_field": null,
          "one_deselect_action": "nullify",
          "one_field": null,
          "sort_field": null
        },
        "schema": {
          "table": "todo_items",
          "column": "user_created",
          "foreign_key_table": "directus_users",
          "foreign_key_column": "id",
          "constraint_name": "todo_items_user_created_foreign",
          "on_update": "NO ACTION",
          "on_delete": "NO ACTION"
        }
      },
      {
        "collection": "todo_lists",
        "field": "user_created",
        "related_collection": "directus_users",
        "meta": {
          "junction_field": null,
          "many_collection": "todo_lists",
          "many_field": "user_created",
          "one_allowed_collections": null,
          "one_collection": "directus_users",
          "one_collection_field": null,
          "one_deselect_action": "nullify",
          "one_field": null,
          "sort_field": null
        },
        "schema": {
          "table": "todo_lists",
          "column": "user_created",
          "foreign_key_table": "directus_users",
          "foreign_key_column": "id",
          "constraint_name": "todo_lists_user_created_foreign",
          "on_update": "NO ACTION",
          "on_delete": "NO ACTION"
        }
      }
    ]
  },
  "hash": "c6de87588f272a9c7932ba1d8c9d8072fef681fc"
}